piepdf/__main__.py
piepdf/adjustUI.py
piepdf/fileWatcher.py
piepdf/infoWidget.py
piepdf/layout.py
piepdf/settings.py
piepdf/database/extractText.py
piepdf/database/metadata.py
piepdf/database/sql.py
piepdf/gscholar/fetchInfo.py
piepdf/gscholar/one.py
piepdf/pdfviewer/fixedARLabel.py
piepdf/pdfviewer/pdfviewer.py
piepdf/pdfviewer/threadedRender.py
piepdf/tags/flowlayout.py
piepdf/tags/line_edit.py
piepdf/tags/tags.py
piepdf-0.1.0.dist-info/licenses/LICENSE
piepdf-0.1.0.dist-info/METADATA
piepdf-0.1.0.dist-info/WHEEL
piepdf-0.1.0.dist-info/entry_points.txt
piepdf-0.1.0.dist-info/top_level.txt
piepdf-0.1.0.dist-info/RECORD
