Metadata-Version: 2.4
Name: piepdf
Version: 0.1.0
Summary: Add your description here
Requires-Python: >=3.12
License-File: LICENSE
Requires-Dist: habanero>=2.0.0
Requires-Dist: pyqt5>=5.15.11
Requires-Dist: pyqt5-sip>=12.16.0
Requires-Dist: pyqtwebengine>=5.15.7
Requires-Dist: python-poppler-qt5>=21.3.0
Requires-Dist: sip>=6.9.0
Requires-Dist: feedparser>=6.0.11
Requires-Dist: httplib2>=0.22.0
Dynamic: license-file
